<?xml version="1.0" encoding="UTF-8"?>
<metadata xml:lang="en"><Esri><CreaDate>20190929</CreaDate><CreaTime>13052000</CreaTime><ArcGISFormat>1.0</ArcGISFormat><SyncOnce>TRUE</SyncOnce><DataProperties><lineage><Process ToolSource="e:\arcgis\desktop10.5\ArcToolbox\Toolboxes\Data Management Tools.tbx\CalculateField" Date="20190915" Time="213907">CalculateField Detroit_Block_Groups_Joined_2 Per_Vacant "[AH36M003] / [AH36M001]" VB #</Process><Process ToolSource="e:\arcgis\desktop10.5\ArcToolbox\Toolboxes\Data Management Tools.tbx\CalculateField" Date="20190915" Time="221212">CalculateField Detroit_Block_Groups_Joined_2 Per_Vacant "[AH36M003] / [AH36M001] * 100" VB #</Process><Process ToolSource="e:\arcgis\desktop10.5\ArcToolbox\Toolboxes\Data Management Tools.tbx\CalculateField" Date="20190915" Time="221306">CalculateField Detroit_Block_Groups_Joined_2 Per_Vacant "([AH36M003] / [AH36M001]) * 100" VB #</Process><Process ToolSource="e:\arcgis\desktop10.5\ArcToolbox\Toolboxes\Data Management Tools.tbx\CalculateField" Date="20190915" Time="222249">CalculateField Detroit_Block_Groups_Joined_2 Per_Vacant "( [AH36E003] / [AH36E001] ) * 100" VB #</Process><Process ToolSource="c:\program files (x86)\arcgis\desktop10.6\ArcToolbox\Toolboxes\Data Management Tools.tbx\CalculateField" Date="20190922" Time="150755">CalculateField Detroit_Block_Groups_Joined_2 GEOID_INT [GEOID] VB #</Process><Process ToolSource="c:\program files (x86)\arcgis\desktop10.6\ArcToolbox\Toolboxes\Data Management Tools.tbx\CalculateField" Date="20190922" Time="150835">CalculateField Detroit_Block_Groups_Joined_2 GEOID_DBL [GEOID] VB #</Process><Process ToolSource="c:\program files (x86)\arcgis\desktop10.6\ArcToolbox\Toolboxes\Data Management Tools.tbx\CalculateField" Date="20190922" Time="151111">CalculateField Detroit_Block_Groups_Joined_2 UNIQUE_ID [FID] VB #</Process><Process ToolSource="e:\arcgis\desktop10.5\ArcToolbox\Toolboxes\Data Management Tools.tbx\Project" Date="20190929" Time="130522">Project C:\Users\Joe\Documents\GitHub\Geo572_Lab1\Data\Detroit_Block_Groups_Joined_2\Detroit_Block_Groups_Joined_2.shp C:\Users\Joe\Documents\GitHub\Geo572_Lab1\Data\Detroit_Block_Groups_Joined_2\Detroit_Block_Groups_Joined_2_proj.shp PROJCS['NAD_1983_Michigan_GeoRef_Meters',GEOGCS['GCS_North_American_1983',DATUM['D_North_American_1983',SPHEROID['GRS_1980',6378137.0,298.257222101]],PRIMEM['Greenwich',0.0],UNIT['Degree',0.0174532925199433]],PROJECTION['Hotine_Oblique_Mercator_Azimuth_Natural_Origin'],PARAMETER['False_Easting',2546731.496],PARAMETER['False_Northing',-4354009.816],PARAMETER['Scale_Factor',0.9996],PARAMETER['Azimuth',337.25556],PARAMETER['Longitude_Of_Center',-86.0],PARAMETER['Latitude_Of_Center',45.30916666666666],UNIT['Meter',1.0]] # PROJCS['USA_Contiguous_Albers_Equal_Area_Conic',GEOGCS['GCS_North_American_1983',DATUM['D_North_American_1983',SPHEROID['GRS_1980',6378137.0,298.257222101]],PRIMEM['Greenwich',0.0],UNIT['Degree',0.0174532925199433]],PROJECTION['Albers'],PARAMETER['False_Easting',0.0],PARAMETER['False_Northing',0.0],PARAMETER['Central_Meridian',-96.0],PARAMETER['Standard_Parallel_1',29.5],PARAMETER['Standard_Parallel_2',45.5],PARAMETER['Latitude_Of_Origin',37.5],UNIT['Meter',1.0]] NO_PRESERVE_SHAPE # NO_VERTICAL</Process></lineage></DataProperties></Esri></metadata>
